cve_database.py
ethereum_rpc_fingerprinter.py
ethereum_rpc_fingerprinter-1.2.0.dist-info/licenses/LICENSE
ethereum_rpc_fingerprinter-1.2.0.dist-info/METADATA
ethereum_rpc_fingerprinter-1.2.0.dist-info/WHEEL
ethereum_rpc_fingerprinter-1.2.0.dist-info/entry_points.txt
ethereum_rpc_fingerprinter-1.2.0.dist-info/top_level.txt
ethereum_rpc_fingerprinter-1.2.0.dist-info/RECORD
