Metadata-Version: 2.4
Name: ethereum-rpc-fingerprinter
Version: 1.2.0
Summary: A comprehensive tool for fingerprinting Ethereum RPC endpoints
Home-page: https://github.com/smolgroot/ethereum-rpc-fingerprinter
Author: smolgroot
Author-email: Smolgroot <smolgroot@no-doxx.com>
Maintainer-email: Smolgroot <smolgroot@no-doxx.com>
License: MIT
Project-URL: Homepage, https://github.com/yourusername/ethereum-rpc-fingerprinter
Project-URL: Documentation, https://github.com/yourusername/ethereum-rpc-fingerprinter#readme
Project-URL: Repository, https://github.com/yourusername/ethereum-rpc-fingerprinter
Project-URL: Bug Reports, https://github.com/yourusername/ethereum-rpc-fingerprinter/issues
Keywords: ethereum,rpc,fingerprinting,blockchain,web3,geth,besu,nethermind,erigon,security,analysis,cve,vulnerability,detection,cli,tool
Classifier: Development Status :: 4 - Beta
Classifier: Intended Audience :: Developers
Classifier: Intended Audience :: System Administrators
Classifier: License :: OSI Approved :: MIT License
Classifier: Operating System :: OS Independent
Classifier: Programming Language :: Python :: 3
Classifier: Programming Language :: Python :: 3.8
Classifier: Programming Language :: Python :: 3.9
Classifier: Programming Language :: Python :: 3.10
Classifier: Programming Language :: Python :: 3.11
Classifier: Programming Language :: Python :: 3.12
Classifier: Topic :: Internet
Classifier: Topic :: Security
Classifier: Topic :: Software Development :: Libraries :: Python Modules
Classifier: Topic :: System :: Networking
Classifier: Topic :: System :: Systems Administration
Requires-Python: >=3.8
License-File: LICENSE
Requires-Dist: web3>=6.0.0
Requires-Dist: requests>=2.28.0
Requires-Dist: aiohttp>=3.8.0
Requires-Dist: colorama>=0.4.4
Requires-Dist: tabulate>=0.9.0
Requires-Dist: pyyaml>=6.0
Requires-Dist: click>=8.0.0
Requires-Dist: rich>=13.0.0
Requires-Dist: packaging>=21.0
Provides-Extra: dev
Requires-Dist: pytest>=7.0.0; extra == "dev"
Requires-Dist: pytest-asyncio>=0.21.0; extra == "dev"
Requires-Dist: black>=22.0.0; extra == "dev"
Requires-Dist: flake8>=5.0.0; extra == "dev"
Requires-Dist: mypy>=1.0.0; extra == "dev"
Requires-Dist: twine>=4.0.0; extra == "dev"
Requires-Dist: build>=0.8.0; extra == "dev"
Dynamic: author
Dynamic: home-page
Dynamic: license-file
Dynamic: requires-python
